odoo8_addon_mrp_bom_version-8.0.1.0.0.99.dev47-py3.8-nspkg.pth
odoo_addons/mrp_bom_version/README.rst
odoo_addons/mrp_bom_version/__init__.py
odoo_addons/mrp_bom_version/__openerp__.py
odoo_addons/mrp_bom_version/data/mrp_bom_data.xml
odoo_addons/mrp_bom_version/i18n/ar.po
odoo_addons/mrp_bom_version/i18n/bg.po
odoo_addons/mrp_bom_version/i18n/bs.po
odoo_addons/mrp_bom_version/i18n/ca.po
odoo_addons/mrp_bom_version/i18n/ca_ES.po
odoo_addons/mrp_bom_version/i18n/cs.po
odoo_addons/mrp_bom_version/i18n/da.po
odoo_addons/mrp_bom_version/i18n/de.po
odoo_addons/mrp_bom_version/i18n/en_GB.po
odoo_addons/mrp_bom_version/i18n/en_US.po
odoo_addons/mrp_bom_version/i18n/es.po
odoo_addons/mrp_bom_version/i18n/es_CR.po
odoo_addons/mrp_bom_version/i18n/es_EC.po
odoo_addons/mrp_bom_version/i18n/es_ES.po
odoo_addons/mrp_bom_version/i18n/es_MX.po
odoo_addons/mrp_bom_version/i18n/es_VE.po
odoo_addons/mrp_bom_version/i18n/et.po
odoo_addons/mrp_bom_version/i18n/fi.po
odoo_addons/mrp_bom_version/i18n/fr.po
odoo_addons/mrp_bom_version/i18n/fr_CH.po
odoo_addons/mrp_bom_version/i18n/gl.po
odoo_addons/mrp_bom_version/i18n/hr.po
odoo_addons/mrp_bom_version/i18n/hr_HR.po
odoo_addons/mrp_bom_version/i18n/hu.po
odoo_addons/mrp_bom_version/i18n/id.po
odoo_addons/mrp_bom_version/i18n/it.po
odoo_addons/mrp_bom_version/i18n/ja.po
odoo_addons/mrp_bom_version/i18n/lt.po
odoo_addons/mrp_bom_version/i18n/mk.po
odoo_addons/mrp_bom_version/i18n/mn.po
odoo_addons/mrp_bom_version/i18n/mrp_bom_version.pot
odoo_addons/mrp_bom_version/i18n/nb.po
odoo_addons/mrp_bom_version/i18n/nb_NO.po
odoo_addons/mrp_bom_version/i18n/nl.po
odoo_addons/mrp_bom_version/i18n/nl_BE.po
odoo_addons/mrp_bom_version/i18n/nl_NL.po
odoo_addons/mrp_bom_version/i18n/pl.po
odoo_addons/mrp_bom_version/i18n/pt.po
odoo_addons/mrp_bom_version/i18n/pt_BR.po
odoo_addons/mrp_bom_version/i18n/pt_PT.po
odoo_addons/mrp_bom_version/i18n/ro.po
odoo_addons/mrp_bom_version/i18n/ru.po
odoo_addons/mrp_bom_version/i18n/sk.po
odoo8_addon_mrp_bom_version-8.0.1.0.0.99.dev47.dist-info/METADATA
odoo8_addon_mrp_bom_version-8.0.1.0.0.99.dev47.dist-info/WHEEL
odoo8_addon_mrp_bom_version-8.0.1.0.0.99.dev47.dist-info/namespace_packages.txt
odoo8_addon_mrp_bom_version-8.0.1.0.0.99.dev47.dist-info/top_level.txt
odoo8_addon_mrp_bom_version-8.0.1.0.0.99.dev47.dist-info/RECORD
